Metadata-Version: 1.0
Name: pms-stats
Version: 0.1
Summary: Gaussian
Home-page: UNKNOWN
Author: UNKNOWN
Author-email: UNKNOWN
License: UNKNOWN
Platform: UNKNOWN
